pyextension/__main__.py
pyextension/pyextension.py
pyextension-1.0.3.dist-info/METADATA
pyextension-1.0.3.dist-info/WHEEL
pyextension-1.0.3.dist-info/entry_points.txt
pyextension-1.0.3.dist-info/top_level.txt
pyextension-1.0.3.dist-info/RECORD
